[
  {
    "date": "2026-05-27",
    "player": "鈴木 誠也 (CHC)",
    "team_vs": "カブス 1 - 12 パイレーツ (試合終了)",
    "batting": {
      "AB": 3,
      "H": 0,
      "HR": 0,
      "RBI": 0,
      "BB": 0,
      "SO": 0,
      "season_avg": ".235",
      "season_hr": 7,
      "season_rbi": 17
    }
  },
  {
    "date": "2026-05-27",
    "player": "大谷 翔平 (LAD)",
    "team_vs": "ロッキーズ 6 - 15 ドジャース (試合終了)",
    "batting": {
      "AB": 2,
      "H": 0,
      "HR": 0,
      "RBI": 0,
      "BB": 0,
      "SO": 0,
      "season_avg": ".270",
      "season_hr": 8,
      "season_rbi": 29
    }
  },
  {
    "date": "2026-05-27",
    "player": "吉田 正尚 (BOS)",
    "team_vs": "ブレーブス 7 - 6 レッドソックス (試合終了)",
    "batting": {
      "AB": 3,
      "H": 0,
      "HR": 0,
      "RBI": 0,
      "BB": 1,
      "SO": 1,
      "season_avg": ".255",
      "season_hr": 1,
      "season_rbi": 7
    }
  },
  {
    "date": "2026-05-27",
    "player": "岡本 和真 (TOR)",
    "team_vs": "マーリンズ 1 - 8 ブルージェイズ (試合終了)",
    "batting": {
      "AB": 4,
      "H": 1,
      "HR": 0,
      "RBI": 1,
      "BB": 0,
      "SO": 2,
      "season_avg": ".215",
      "season_hr": 10,
      "season_rbi": 28
    }
  },
  {
    "date": "2026-05-27",
    "player": "村上 宗隆 (CWS)",
    "team_vs": "ツインズ 5 - 3 ホワイトソックス (試合終了)",
    "batting": {
      "AB": 5,
      "H": 1,
      "HR": 1,
      "RBI": 2,
      "BB": 0,
      "SO": 1,
      "season_avg": ".234",
      "season_hr": 19,
      "season_rbi": 39
    }
  }
]